CHANGELOG.md
dicommeta/Struct.py
dicommeta/Utils.py
dicommeta/__init__.py
dicommeta-0.6.7.dist-info/LICENSE
dicommeta-0.6.7.dist-info/METADATA
dicommeta-0.6.7.dist-info/WHEEL
dicommeta-0.6.7.dist-info/RECORD
