Metadata-Version: 2.1
Name: dicommeta
Version: 0.6.7
Summary: Dicom Metadata structures
Home-page: https://dev.azure.com/longke/Radiology/_git/DicomMeta
Author: Kevin Long
Author-email: longke@pennmedicine.upenn.edu
Maintainer: Kevin Long
Maintainer-email: longke@pennmedicine.upenn.edu
Requires-Python: >=3.10,<4.0
Classifier: Programming Language :: Python :: 3
Classifier: Programming Language :: Python :: 3.10
Classifier: Programming Language :: Python :: 3.11
Requires-Dist: attrs (>=23.1.0,<24.0.0)
Requires-Dist: python-dateutil (>=2.8.2,<3.0.0)
Project-URL: Repository, https://dev.azure.com/longke/Radiology/_git/DicomMeta
